djangoldp_hd/__init__.py
djangoldp_hd/agents.py
djangoldp_hd/apps.py
djangoldp_hd/settings.py
djangoldp_hd/migrations/__init__.py
djangoldp_hd-0.2.7.dist-info/METADATA
djangoldp_hd-0.2.7.dist-info/WHEEL
djangoldp_hd-0.2.7.dist-info/top_level.txt
djangoldp_hd-0.2.7.dist-info/RECORD
